setup.cfg
setup.py
txsimplegeo/__init__.py
txsimplegeo.shared.egg-info/PKG-INFO
txsimplegeo.shared.egg-info/SOURCES.txt
txsimplegeo.shared.egg-info/dependency_links.txt
txsimplegeo.shared.egg-info/namespace_packages.txt
txsimplegeo.shared.egg-info/not-zip-safe
txsimplegeo.shared.egg-info/requires.txt
txsimplegeo.shared.egg-info/top_level.txt
txsimplegeo/shared/__init__.py
txsimplegeo/shared/_version.py
txsimplegeo/shared/oauth.py
txsimplegeo/shared/test/__init__.py
txsimplegeo/shared/test/test_client.py
txsimplegeo/shared/test/test_oauth.py
txsimplegeo/shared/test/test_record.py