Metadata-Version: 1.0
Name: txsimplegeo.shared
Version: 0.9.83
Summary: Twisted library for interfacing with SimpleGeo's API
Home-page: http://github.com/simplegeo/python-txsimplegeo.shared
Author: Zooko Wilcox-O'Hearn
Author-email: zooko@simplegeo.com
License: MIT License
Keywords: simplegeo
Platform: UNKNOWN
